{
    "AccountFormController": 2,
    "Account": 1,
    "AccountForm": 2,
    "AccountValidator": 2,
    "PetStoreImpl": 1,
    "UserSession": 1,
    "AddItemToCartController": 0,
    "Cart": 0,
    "CartItem": 0,
    "Item": 0,
    "Category": 1,
    "LineItem": 1,
    "Order": 1,
    "OrderFormController": 3,
    "OrderForm": 3,
    "OrderValidator": 3,
    "SqlMapAccountDao": 1,
    "SqlMapCategoryDao": 1,
    "SqlMapItemDao": 1,
    "SqlMapOrderDao": 1,
    "SqlMapProductDao": 1,
    "RemoveItemFromCartController": 1,
    "ListOrdersController": 1,
    "Product": 1,
    "SearchProductsController": 1,
    "SignoffController": 1,
    "SignonController": 1,
    "SignonInterceptor": 1,
    "UpdateCartQuantitiesController": 0,
    "ViewCartController": 0,
    "ViewCategoryController": 1,
    "ViewItemController": 0,
    "ViewOrderController": 1,
    "ViewProductController": 1,
    "SqlMapSequenceDao": 1,
    "SqlMapProductDao::ProductSearch": 1,
    "Sequence": 1
}