{
    "AcmeAirConfiguration": 0,
    "AuthServiceImpl": 0,
    "BookingServiceImpl": 0,
    "CustomerServiceImpl": 0,
    "FlightServiceImpl": 0,
    "ServiceLocator": 0,
    "AuthService": 4,
    "KeyGenerator": 0,
    "ConnectionManager": 0,
    "BookingLoader": 3,
    "BookingsREST": 0,
    "CustomerLoader": 3,
    "CustomerREST": 0,
    "CustomerInfo": 0,
    "CustomerService": 0,
    "FlightLoader": 3,
    "AirportCodeMapping": 0,
    "FlightService": 0,
    "FlightsREST": 4,
    "Loader": 3,
    "SessionLoader": 3,
    "LoaderREST": 3,
    "LoginREST": 4,
    "RESTCookieSessionFilter": 4,
    "AcmeAirApp": 4,
    "AddressInfo": 0,
    "AppConfig": 1,
    "SupportWebSocket": 2
}